json_type/__about__.py
json_type/__init__.py
json_type-0.0.1.dist-info/METADATA
json_type-0.0.1.dist-info/WHEEL
json_type-0.0.1.dist-info/licenses/LICENSE.txt
json_type-0.0.1.dist-info/RECORD
